attini_cdk/__init__.py
attini_cdk/py.typed
attini_cdk/_jsii/__init__.py
attini_cdk/_jsii/cdk@1.4.1.jsii.tgz
attini_cdk_lib-1.4.1.dist-info/LICENSE
attini_cdk_lib-1.4.1.dist-info/METADATA
attini_cdk_lib-1.4.1.dist-info/WHEEL
attini_cdk_lib-1.4.1.dist-info/top_level.txt
attini_cdk_lib-1.4.1.dist-info/RECORD
